GSMM_transcriptome_data_mapper/__init__.py
GSMM_transcriptome_data_mapper/transcriptome_mapper.py
gsmm_transcriptome_data_mapper-0.0.1.dist-info/METADATA
gsmm_transcriptome_data_mapper-0.0.1.dist-info/WHEEL
gsmm_transcriptome_data_mapper-0.0.1.dist-info/licenses/LICENSE
gsmm_transcriptome_data_mapper-0.0.1.dist-info/RECORD
