Metadata-Version: 2.1
Name: GSMM_transcriptome_data_mapper
Version: 0.0.1
Summary: A package to map transcriptome data to constrain reactions of a genome scale metabolic model
Project-URL: Homepage, https://github.com/Sookie-S/Mapping-of-transcriptome-data-to-genome-scale-scale-model-reactions
Project-URL: Bug Tracker, https://github.com/Sookie-S/Mapping-of-transcriptome-data-to-genome-scale-scale-model-reactions/issues
Author-email: Soukaina Timouma <soukaina.timouma@gmail.com>
License-File: LICENSE
Classifier: License :: OSI Approved :: MIT License
Classifier: Operating System :: OS Independent
Classifier: Programming Language :: Python :: 3
Requires-Python: >=3.7
